endpoint_wrapper/__init__.py
endpoint_wrapper/wrapper.py
endpoint_wrapper/util/__init__.py
endpoint_wrapper/util/basic.py
endpoint_wrapper/util/handle_error.py
endpoint_wrapper-1.0.12.dist-info/LICENSE
endpoint_wrapper-1.0.12.dist-info/METADATA
endpoint_wrapper-1.0.12.dist-info/WHEEL
endpoint_wrapper-1.0.12.dist-info/top_level.txt
endpoint_wrapper-1.0.12.dist-info/RECORD
